pypads/__init__.py
pypads/app/__init__.py
pypads/app/actuators.py
pypads/app/api.py
pypads/app/backends/__init__.py
pypads/app/backends/backend.py
pypads/app/backends/mlflow.py
pypads/app/backends/repository.py
pypads/app/base.py
pypads/app/call.py
pypads/app/decorators.py
pypads/app/env.py
pypads/app/injections/__init__.py
pypads/app/injections/base_logger.py
pypads/app/injections/injection.py
pypads/app/injections/run_loggers.py
pypads/app/injections/tracked_object.py
pypads/app/misc/__init__.py
pypads/app/misc/caches.py
pypads/app/misc/extensions.py
pypads/app/misc/inheritance.py
pypads/app/misc/managed_git.py
pypads/app/misc/mixins.py
pypads/app/pypads.py
pypads/app/results.py
pypads/app/validators.py
pypads/arguments.py
pypads/bindings/__init__.py
pypads/bindings/anchors.py
pypads/bindings/event_types.py
pypads/bindings/events.py
pypads/bindings/hooks.py
pypads/bindings/resources/__init__.py
pypads/bindings/resources/mapping/__init__.py
pypads/bindings/resources/mapping/keras.2_3_1.yml
pypads/bindings/resources/mapping/sklearn_0_19_1.yml
pypads/bindings/resources/mapping/tensorflow_2_3_0.yml
pypads/definitions.py
pypads/exceptions.py
pypads/importext/__init__.py
pypads/importext/mappings.py
pypads/importext/package_path.py
pypads/importext/pypads_import.py
pypads/importext/semver/__init__.py
pypads/importext/semver/empty_constraint.py
pypads/importext/semver/exceptions.py
pypads/importext/semver/patterns.py
pypads/importext/semver/version.py
pypads/importext/semver/version_constraint.py
pypads/importext/semver/version_range.py
pypads/importext/semver/version_union.py
pypads/importext/versioning.py
pypads/importext/wrapping/__init__.py
pypads/importext/wrapping/base_wrapper.py
pypads/importext/wrapping/class_wrapping.py
pypads/importext/wrapping/function_wrapping.py
pypads/importext/wrapping/module_wrapping.py
pypads/importext/wrapping/wrapping.py
pypads/injections/__init__.py
pypads/injections/analysis/__init__.py
pypads/injections/analysis/call_tracker.py
pypads-0.5.7.dist-info/LICENSE
pypads-0.5.7.dist-info/WHEEL
pypads-0.5.7.dist-info/METADATA
pypads-0.5.7.dist-info/RECORD
