Metadata-Version: 2.1
Name: pypads
Version: 0.5.7
Summary: PyPaDS aims to to add tracking functionality to machine learning libraries.
Home-page: https://www.padre-lab.eu/
License: GPL-3.0-or-later
Keywords: tracking,reproducibility,provenance,function injection,mapping files
Author: Thomas Weißgerber
Author-email: thomas.weissgerber@uni-passau.de
Requires-Python: >=3.6.0,<4.0.0
Classifier: Development Status :: 3 - Alpha
Classifier: Intended Audience :: Developers
Classifier: Intended Audience :: Science/Research
Classifier: License :: OSI Approved :: GNU General Public License v3 or later (GPLv3+)
Classifier: Natural Language :: English
Classifier: Operating System :: MacOS
Classifier: Operating System :: Microsoft :: Windows
Classifier: Operating System :: Unix
Classifier: Programming Language :: Python :: 3
Classifier: Programming Language :: Python :: 3.6
Classifier: Programming Language :: Python :: 3.7
Classifier: Programming Language :: Python :: 3.8
Classifier: Programming Language :: Python :: 3.9
Classifier: Topic :: Scientific/Engineering :: Artificial Intelligence
Provides-Extra: docs
Requires-Dist: boltons (>=19.3.0,<20.0.0)
Requires-Dist: cloudpickle (>=1.3.0,<2.0.0)
Requires-Dist: jsonpath-rw (>=1.4.0,<2.0.0)
Requires-Dist: jsonpath-rw-ext (>=1.2.2,<2.0.0)
Requires-Dist: loguru (>=0.4.1,<0.5.0)
Requires-Dist: mlflow (>=1.12.1,<2.0.0)
Requires-Dist: pydantic (>=1.5.1,<2.0.0)
Requires-Dist: pymongo (==3.11.0)
Project-URL: Documentation, https://pypads.readthedocs.io/en/latest/
Project-URL: Repository, https://github.com/padre-lab-eu/pypads
